icdar_tools/__init__.py
icdar_tools/data_util.py
icdar_tools/icd_util.py
icdar_tools/icdar.py
icdar_tools/locality_aware_nms.py
icdar_tools-0.0.3.dist-info/METADATA
icdar_tools-0.0.3.dist-info/RECORD
icdar_tools-0.0.3.dist-info/WHEEL
icdar_tools-0.0.3.dist-info/top_level.txt
