Metadata-Version: 2.1
Name: icdar-tools
Version: 0.0.3
Summary: a pip install icdar_tools
Home-page: UNKNOWN
Author: mlib_4_you
Author-email: none.none@gmail.com
License: MIT
Keywords: icdar data tools,East tools
Platform: UNKNOWN
Classifier: Programming Language :: Python :: 3
Classifier: License :: OSI Approved :: MIT License
Classifier: Operating System :: OS Independent
Requires-Dist: shapely
